{
  "allProducts": [
    {
      "id": "888",
      "image": "mobile.jpg",
      "name": "honor",
      "price": "25000",
      "quantity": "30",
      "category": "mobiles",
      "status": "In Stock"
    },
    {
      "id": "10003",
      "image": "mobile.jpg",
      "name": "sumsung",
      "price": "900",
      "quantity": "25",
      "category": "electronics",
      "status": "out of stock"
    },
    {
      "id": "4432",
      "image": "logo.png",
      "name": "shoe",
      "price": "5",
      "quantity": "15",
      "category": "shoes",
      "status": "instock"
    },
    {
      "id": "65",
      "image": "mobile.jpg",
      "name": "redme",
      "price": "2",
      "quantity": "20",
      "category": "phone",
      "status": "instock"
    },
    {
      "id": "11",
      "image": "mobile.jpg",
      "name": "nokia",
      "price": "3",
      "quantity": "11",
      "category": "Electronics",
      "status": "instock"
    }
  ],
  "newuser": [
    {
      "firstName": "miruna",
      "lastName": "lini",
      "emailAddress": "miru@gmail.com",
      "pwd": "adc",
      "id": ""
    },
    {
      "firstName": "miruna",
      "lastName": "fgggggg",
      "emailAddress": "@gmail.com",
      "pwd": "777777",
      "id": "zu1QP4Z"
    },
    {
      "firstName": "kavitha",
      "lastName": "Rajaji",
      "emailAddress": "@gmail.com",
      "pwd": "7777777",
      "id": "ywqkdOQ"
    },
    {
      "firstName": "miruna",
      "lastName": "kavitha",
      "emailAddress": "miru@gmail.com",
      "pwd": "asdfgh",
      "id": "V26DjGM"
    },
    {
      "firstName": "iiiiii",
      "lastName": "hkkkkd",
      "emailAddress": "a@gmail.com",
      "pwd": "123456",
      "id": "85Jr_Be"
    },
    {
      "firstName": "kabith",
      "lastName": "hythum",
      "emailAddress": "mirunalini@yahoo.com",
      "pwd": "miruna",
      "id": "1uDPtEP"
    },
    {
      "firstName": "jihuln",
      "lastName": "lkudbm",
      "emailAddress": "miruna@gmail.com",
      "pwd": "123456",
      "id": "Tbnxauh"
    },
    {
      "firstName": "fffffff",
      "lastName": "fffffff",
      "emailAddress": "@ail.com",
      "pwd": "4444444",
      "id": "m0Zp-gK"
    },
    {
      "firstName": "hdkfkjf",
      "lastName": "yyyyyu",
      "emailAddress": "l@gmail.com",
      "pwd": "7777777",
      "id": "Q-14GO5"
    },
    {
      "firstName": "rajaji",
      "lastName": "kavitha",
      "emailAddress": "11@gmail.com",
      "pwd": "1234567",
      "id": "5iNhjeZ"
    },
    {
      "firstName": "liniya",
      "lastName": "miruna",
      "emailAddress": "lini@gmail.com",
      "pwd": "zzzzzz",
      "id": "JHpp8J1"
    },
    {
      "firstName": "jjjjj",
      "lastName": "jjjjj",
      "emailAddress": "jj@gmail.com",
      "pwd": "1111111",
      "id": "E2PHySQ"
    },
    {
      "firstName": "hello",
      "lastName": "hello",
      "emailAddress": "22@gmail.com",
      "pwd": "111111",
      "id": "oTcaVyM"
    },
    {
      "firstName": "sobitha",
      "lastName": "rajaji",
      "emailAddress": "sobi@gmail.com",
      "pwd": "1234567890",
      "id": "8cGgPgG"
    },
    {
      "firstName": "niveth",
      "lastName": "gopik",
      "emailAddress": "nive@gmail.com",
      "pwd": "222222",
      "id": "1SvLZVx"
    }
  ],
  "sampleProducts": [
    {
      "id": "1",
      "name": "Sumsung",
      "price": "25000",
      "quantity": "5",
      "category": "Mobile",
      "status": "Available"
    },
    {
      "id": "2",
      "name": "jbl",
      "price": "256",
      "quantity": "12",
      "category": "ear phone",
      "status": "true"
    },
    {
      "id": "3",
      "name": "ear phone",
      "price": "4444",
      "quantity": "66",
      "category": "ear phone",
      "status": "on"
    },
    {
      "id": "8",
      "name": "ff",
      "price": "66",
      "quantity": "5",
      "category": "hhh",
      "status": "on"
    },
    {
      "id": "4",
      "name": "ff",
      "price": "55",
      "quantity": "2",
      "category": "cc",
      "status": "true"
    },
    {
      "id": "6",
      "name": "der",
      "price": "66",
      "quantity": "2",
      "category": "fr",
      "status": "on"
    }
  ]
}